likob/__init__.py
likob/cli.py
likob/main.py
likob/docs/__init__.py
likob/examples/__init__.py
likob/examples/advanced_usage.py
likob/examples/basic_usage.py
likob/src/__init__.py
likob/src/core/__init__.py
likob/src/core/database.py
likob/src/core/exceptions.py
likob/src/core/index.py
likob/src/core/table.py
likob/src/core/transaction.py
likob/src/sql/__init__.py
likob/src/sql/executor.py
likob/src/sql/lexer.py
likob/src/sql/parser.py
likob/src/storage/__init__.py
likob/src/storage/engine.py
likob/src/storage/io_manager.py
likob/src/utils/__init__.py
likob/src/utils/config.py
likob/src/utils/logger.py
likob/tests/__init__.py
likob/tests/test_database.py
likob/tests/test_parser.py
likob/tests/test_storage.py
likob-1.0.3.dist-info/METADATA
likob-1.0.3.dist-info/WHEEL
likob-1.0.3.dist-info/entry_points.txt
likob-1.0.3.dist-info/top_level.txt
likob-1.0.3.dist-info/RECORD
